
  { "stem" : "betoken",
    "instances" : 
    [ 
      { "docId" : "librarium_The_Consolations_of_Prayer",
        "docUri" : "librarium\/The_Consolations_of_Prayer.html",
        "score" : 1,
        "contexts" : 
        [ 
          { "form" : "betoken",
            "weight" : "1",
            "pos" : 98,
            "context" : "...sacraments of prayer and devotion. The three-sided shrines <mark>betoken<\/mark> the three-faced benison of Almsivi, and may be...",
            "fid" : "content" } ] } ] }