
  { "stem" : "branora",
    "instances" : 
    [ 
      { "docId" : "librarium_morrowindTables",
        "docUri" : "librarium\/morrowindTables.html",
        "score" : 3,
        "contexts" : 
        [ 
          { "form" : "branora",
            "weight" : "1",
            "pos" : 3853,
            "context" : "tel <mark>branora<\/mark>",
            "fid" : "loc",
            "in" : 
            [ "ssCtx3" ] },
          
          { "form" : "branora",
            "weight" : "1",
            "pos" : 3893,
            "context" : "tel <mark>branora<\/mark>, therana's chamber",
            "fid" : "loc",
            "in" : 
            [ "ssCtx3" ] },
          
          { "form" : "branora",
            "weight" : "1",
            "pos" : 3902,
            "context" : "tel <mark>branora<\/mark>, upper tower",
            "fid" : "loc",
            "in" : 
            [ "ssCtx3" ] } ] },
      
      { "docId" : "librarium_Guide_to_Vivec",
        "docUri" : "librarium\/Guide_to_Vivec.html",
        "score" : 2,
        "contexts" : 
        [ 
          { "form" : "Branora",
            "weight" : "1",
            "pos" : 612,
            "context" : "...to Ebonheart, Hla Oad, Molag Mar, and Tel <mark>Branora<\/mark>. Ships from nearby Ebonheart sail to Hla Oad, Sadrith...",
            "fid" : "content" },
          
          { "form" : "Branora",
            "weight" : "1",
            "pos" : 622,
            "context" : "...nearby Ebonheart sail to Hla Oad, Sadrith Mora, Tel <mark>Branora<\/mark>, and the Foreign Quarter of Vivec. Low-fare...",
            "fid" : "content" } ] },
      
      { "docId" : "librarium_Guide_to_Vvardenfell",
        "docUri" : "librarium\/Guide_to_Vvardenfell.html",
        "score" : 2,
        "contexts" : 
        [ 
          { "form" : "Branora",
            "weight" : "1",
            "pos" : 467,
            "context" : "...wizard towers at Tel Aruhn, Tel Mora, and Tel <mark>Branora<\/mark>, and Ahemmusa camp and the remote fishing villages of Ald...",
            "fid" : "content" },
          
          { "form" : "Branora",
            "weight" : "1",
            "pos" : 527,
            "context" : " Tel <mark>Branora<\/mark> is the tower and seat of the eccentric Telvanni wizard named...",
            "fid" : "content" } ] },
      
      { "docId" : "librarium_The_Affairs_of_Wizards",
        "docUri" : "librarium\/The_Affairs_of_Wizards.html",
        "score" : 2,
        "contexts" : 
        [ 
          { "form" : "Branora",
            "weight" : "1",
            "pos" : 40,
            "context" : "Tel <mark>Branora<\/mark>, Upper Tower: Visitable? yes",
            "fid" : "acq" },
          
          { "form" : "Branora",
            "weight" : "1",
            "pos" : 46,
            "context" : "Tel <mark>Branora<\/mark>, Therana's Chamber: Visitable? yes",
            "fid" : "acq" } ] },
      
      { "docId" : "librarium_Brown_Book_of_3E_426",
        "docUri" : "librarium\/Brown_Book_of_3E_426.html",
        "score" : 1,
        "contexts" : 
        [ 
          { "form" : "Branora",
            "weight" : "1",
            "pos" : 89,
            "context" : "...Lord of Telvanni Council, Vvardenfell District, Tower of Tel <mark>Branora<\/mark>, Azura's Coast, District of Vvardenfell, Province of Morrowind...",
            "fid" : "content" } ] },
      
      { "docId" : "librarium_Guide_to_Sadrith_Mora",
        "docUri" : "librarium\/Guide_to_Sadrith_Mora.html",
        "score" : 1,
        "contexts" : 
        [ 
          { "form" : "Branora",
            "weight" : "1",
            "pos" : 318,
            "context" : "...Arethi at the docks offers ship passage to Ebonheart, Tel <mark>Branora<\/mark>, Tel Mora, or Dagon Fel. Iniel at the...",
            "fid" : "content" } ] },
      
      { "docId" : "librarium_Homilies_of_Blessed_Almalexia",
        "docUri" : "librarium\/Homilies_of_Blessed_Almalexia.html",
        "score" : 1,
        "contexts" : 
        [ 
          { "form" : "Branora",
            "weight" : "1",
            "pos" : 9,
            "context" : "Tel <mark>Branora<\/mark>: Visitable? yes",
            "fid" : "acq" } ] },
      
      { "docId" : "librarium_the_book_of_dawn_n_dusk",
        "docUri" : "librarium\/the_book_of_dawn_n_dusk.html",
        "score" : 1,
        "contexts" : 
        [ 
          { "form" : "Branora",
            "weight" : "1",
            "pos" : 60,
            "context" : "Tel <mark>Branora<\/mark>: Visitable? yes",
            "fid" : "acq" } ] },
      
      { "docId" : "librarium_The_Cantatas_of_Vivec",
        "docUri" : "librarium\/The_Cantatas_of_Vivec.html",
        "score" : 1,
        "contexts" : 
        [ 
          { "form" : "Branora",
            "weight" : "1",
            "pos" : 37,
            "context" : "Tel <mark>Branora<\/mark>: Visitable? yes",
            "fid" : "acq" } ] },
      
      { "docId" : "librarium_The_Consolations_of_Prayer",
        "docUri" : "librarium\/The_Consolations_of_Prayer.html",
        "score" : 1,
        "contexts" : 
        [ 
          { "form" : "Branora",
            "weight" : "1",
            "pos" : 53,
            "context" : "Tel <mark>Branora<\/mark>: Visitable? yes",
            "fid" : "acq" } ] } ] }