
  { "stem" : "hollow",
    "instances" : 
    [ 
      { "docId" : "librarium_Great_Houses_of_Morrowind",
        "docUri" : "librarium\/Great_Houses_of_Morrowind.html",
        "score" : 1,
        "contexts" : 
        [ 
          { "form" : "hollowed",
            "weight" : "1",
            "pos" : 427,
            "context" : "...native mushrooms. Telvanni villages are comprised of smaller mushroom pods <mark>hollowed<\/mark> out for craftsmen and commoners. Open-air markets often...",
            "fid" : "content" } ] } ] }