
  { "stem" : "kena",
    "instances" : 
    [ 
      { "docId" : "librarium_The_Four_Suitors_of_Benitah",
        "docUri" : "librarium\/The_Four_Suitors_of_Benitah.html",
        "score" : 16,
        "contexts" : 
        [ 
          { "form" : "Kena",
            "weight" : "1",
            "pos" : 172,
            "context" : "..., Oin began to sell his herbs, including some to <mark>Kena<\/mark> Kena Yakin Bael, a prominent healer in town. He...",
            "fid" : "content" },
          
          { "form" : "Kena",
            "weight" : "1",
            "pos" : 173,
            "context" : "...Oin began to sell his herbs, including some to Kena <mark>Kena<\/mark> Yakin Bael, a prominent healer in town. He had...",
            "fid" : "content" },
          
          { "form" : "Kena",
            "weight" : "1",
            "pos" : 208,
            "context" : "..., despite all the skills of the great healers, including <mark>Kena<\/mark> Yakin Bael. When Oin came to deliver the herbs that...",
            "fid" : "content" },
          
          { "form" : "Kena",
            "weight" : "1",
            "pos" : 305,
            "context" : "\"I am <mark>Kena<\/mark> Warfel Tomasin, and I can prove that Akatosh, Nirn...",
            "fid" : "content" },
          
          { "form" : "Kena",
            "weight" : "1",
            "pos" : 319,
            "context" : "\"I am <mark>Kena<\/mark> Zombel Mokafa, and I can prove that you do not...",
            "fid" : "content" },
          
          { "form" : "Kena",
            "weight" : "1",
            "pos" : 331,
            "context" : "...wrote out the mathematical formula, which proved correct, and <mark>Kena<\/mark> Warfel Tomasin vaporized on the spot.",
            "fid" : "content" },
          
          { "form" : "Kena",
            "weight" : "1",
            "pos" : 349,
            "context" : "...in the province. Oin went to visit his friend, <mark>Kena<\/mark> Yakin Bael.",
            "fid" : "content" },
          
          { "form" : "Kena",
            "weight" : "1",
            "pos" : 356,
            "context" : "\"Her lady Benitah has heard of the intelligence of <mark>Kena<\/mark> Zombel Mokafa, and has said that she was mistaken....",
            "fid" : "content" },
          
          { "form" : "\"Kena",
            "weight" : "1",
            "pos" : 442,
            "context" : "...,\" said the fellow, nudging the witch next to him. <mark>\"Kena<\/mark> Leles, cast a ball of blue flame for me.\" And...",
            "fid" : "content" },
          
          { "form" : "\"Kena",
            "weight" : "1",
            "pos" : 461,
            "context" : "...Combova, my name is Master Vomph,\" said Oin. <mark>\"Kena<\/mark> Leles, cast a ball of blue flames for me.\" Oin...",
            "fid" : "content" },
          
          { "form" : "Kena",
            "weight" : "1",
            "pos" : 488,
            "context" : "...in the province. Oin went to visit his friend, <mark>Kena<\/mark> Yakin Bael.",
            "fid" : "content" },
          
          { "form" : "Kena",
            "weight" : "1",
            "pos" : 654,
            "context" : "...in the province. Oin went to visit his friend, <mark>Kena<\/mark> Yakin Bael. The door was closed this time and he...",
            "fid" : "content" },
          
          { "form" : "Kena",
            "weight" : "1",
            "pos" : 667,
            "context" : "\"Have you heard about the remarkable Gazouf Mough?\" <mark>Kena<\/mark> Yakin Bael was asking. \"He sounds like a very promising...",
            "fid" : "content" },
          
          { "form" : "kena",
            "weight" : "1",
            "pos" : 676,
            "context" : "\"The truth is, <mark>kena<\/mark>, that I have no more interest in him that I...",
            "fid" : "content" },
          
          { "form" : "Kena",
            "weight" : "1",
            "pos" : 680,
            "context" : "...interest in him that I had in Nimlom the Mighty, <mark>Kena<\/mark> Zombel Mokafa, or Master Vomph,\" replied a feminine voice...",
            "fid" : "content" },
          
          { "form" : "Kena",
            "weight" : "1",
            "pos" : 747,
            "context" : "...were married at once. A week later, he returned to <mark>Kena<\/mark> Yakin Bael and learned how to fortify his personality in exchange...",
            "fid" : "content" } ] } ] }