
  { "stem" : "realli",
    "instances" : 
    [ 
      { "docId" : "librarium_buyn_game_EX",
        "docUri" : "librarium\/buyn_game_EX.html",
        "score" : 2,
        "contexts" : 
        [ 
          { "form" : "really",
            "weight" : "1",
            "pos" : 28,
            "context" : "...a very sad state of affairs, when the game is <mark>really<\/mark> open to all, you don't need an invitation. And it...",
            "fid" : "content" },
          
          { "form" : "really",
            "weight" : "1",
            "pos" : 246,
            "context" : " If you see something you <mark>really<\/mark> like or need, buy it then and there at the...",
            "fid" : "content" } ] },
      
      { "docId" : "librarium_Unnamed_Book",
        "docUri" : "librarium\/Unnamed_Book.html",
        "score" : 1,
        "contexts" : 
        [ 
          { "form" : "really",
            "weight" : "1",
            "pos" : 36,
            "context" : "...some pride, some skill, some basic creativity. It <mark>really<\/mark> makes those of us with a sense of history despair.\"...",
            "fid" : "content" } ] } ] }