
  { "stem" : "shara",
    "instances" : 
    [ 
      { "docId" : "librarium_Blasphemous_Revenants",
        "docUri" : "librarium\/Blasphemous_Revenants.html",
        "score" : 1,
        "contexts" : 
        [ 
          { "form" : "Shara",
            "weight" : "1",
            "pos" : 50,
            "context" : "<mark>Shara<\/mark>: Visitable? yes",
            "fid" : "acq" } ] },
      
      { "docId" : "librarium_morrowindTables",
        "docUri" : "librarium\/morrowindTables.html",
        "score" : 1,
        "contexts" : 
        [ 
          { "form" : "shara",
            "weight" : "1",
            "pos" : 3577,
            "context" : "<mark>shara<\/mark>",
            "fid" : "loc",
            "in" : 
            [ "ssCtx3" ] } ] },
      
      { "docId" : "librarium_Reflections_on_Cult_Worship",
        "docUri" : "librarium\/Reflections_on_Cult_Worship.html",
        "score" : 1,
        "contexts" : 
        [ 
          { "form" : "Shara",
            "weight" : "1",
            "pos" : 43,
            "context" : "<mark>Shara<\/mark>: Visitable? yes",
            "fid" : "acq" } ] },
      
      { "docId" : "librarium_Vampires_of_Vvardenfell",
        "docUri" : "librarium\/Vampires_of_Vvardenfell.html",
        "score" : 1,
        "contexts" : 
        [ 
          { "form" : "Shara",
            "weight" : "1",
            "pos" : 58,
            "context" : "<mark>Shara<\/mark>: Visitable? yes",
            "fid" : "acq" } ] } ] }