
  { "stem" : "sometim",
    "instances" : 
    [ 
      { "docId" : "librarium_For_my_Gods_and_Emperor",
        "docUri" : "librarium\/For_my_Gods_and_Emperor.html",
        "score" : 2,
        "contexts" : 
        [ 
          { "form" : "sometimes",
            "weight" : "1",
            "pos" : 463,
            "context" : "...hurt in poor and isolated communities. It is difficult and <mark>sometimes<\/mark> dangerous work, but the spiritual rewards are great. Lay...",
            "fid" : "content" },
          
          { "form" : "sometimes",
            "weight" : "1",
            "pos" : 551,
            "context" : "...order at the shrines, carries messages and packages, and <mark>sometimes<\/mark> escorts priests and lay servants on dangerous missions. This occasional...",
            "fid" : "content" } ] },
      
      { "docId" : "librarium_buyn_game_EX",
        "docUri" : "librarium\/buyn_game_EX.html",
        "score" : 1,
        "contexts" : 
        [ 
          { "form" : "sometimes",
            "weight" : "1",
            "pos" : 214,
            "context" : "...something. Similarly, Nords, Bretons, and Cyrodiils are <mark>sometimes<\/mark> treated coolly by merchants in the Summurset Isles. Of course...",
            "fid" : "content" } ] },
      
      { "docId" : "librarium_Corpse_Preparation_v_I",
        "docUri" : "librarium\/Corpse_Preparation_v_I.html",
        "score" : 1,
        "contexts" : 
        [ 
          { "form" : "sometimes",
            "weight" : "1",
            "pos" : 445,
            "context" : "...have died a natural death, a more expedient approach is <mark>sometimes<\/mark> necessary to further the study of the Art.",
            "fid" : "content" } ] },
      
      { "docId" : "librarium_Unnamed_Book",
        "docUri" : "librarium\/Unnamed_Book.html",
        "score" : 1,
        "contexts" : 
        [ 
          { "form" : "sometime",
            "weight" : "1",
            "pos" : 365,
            "context" : "Imalyn laughed loudly, \"Can I see a demonstration <mark>sometime<\/mark>?\"",
            "fid" : "content" } ] } ] }